kb_server/MANIFEST.in
kb_server/README
kb_server/config.py
kb_server/kloudbuster-swagger.yaml
kb_server/setup.cfg
kb_server/setup.py
kb_server/kb_server/__init__.py
kb_server/kb_server/app.py
kb_server/kb_server/controllers/__init__.py
kb_server/kb_server/controllers/api_cfg.py
kb_server/kb_server/controllers/api_kb.py
kb_server/kb_server/controllers/kb_session.py
kb_server/kb_server/controllers/root.py
kb_server/kb_server/hooks/__init__.py
kb_server/kb_server/hooks/cors.py
kb_server/kb_server/model/__init__.py
kb_server/public/README.rst
kb_server/public/ui/favicon.ico
kb_server/public/ui/index.html
kb_server/public/ui/components/angular-1.4.10/angular.min.js
kb_server/public/ui/components/angular-animate-1.4.10/angular-animate.min.js
kb_server/public/ui/components/angular-aria-1.5.2/angular-aria.min.js
kb_server/public/ui/components/angular-bootstrap-0.13.4/ui-bootstrap-tpls.min.js
kb_server/public/ui/components/angular-cookies-1.4.10/angular-cookies.min.js
kb_server/public/ui/components/angular-loading-bar-0.8.0/build/loading-bar.min.css
kb_server/public/ui/components/angular-loading-bar-0.8.0/build/loading-bar.min.js
kb_server/public/ui/components/angular-material-0.11.4/angular-material.min.css
kb_server/public/ui/components/angular-material-0.11.4/angular-material.min.js
kb_server/public/ui/components/angular-messages-1.4.10/angular-messages.min.js
kb_server/public/ui/components/angular-resource-1.4.10/angular-resource.min.js
kb_server/public/ui/components/angular-route-1.4.10/angular-route.min.js
kb_server/public/ui/components/angular-sanitize-1.4.10/angular-sanitize.min.js
kb_server/public/ui/components/angular-touch-1.4.10/angular-touch.min.js
kb_server/public/ui/components/bootstrap-3.3.6/dist/css/bootstrap.min.css
kb_server/public/ui/components/bootstrap-3.3.6/dist/js/bootstrap.min.js
kb_server/public/ui/components/d3-3.5.16/d3.min.js
kb_server/public/ui/components/jquery-2.2.2/dist/jquery.min.js
kloudbuster-8.0.0.dist-info/DESCRIPTION.rst
kloudbuster-8.0.0.dist-info/METADATA
kloudbuster-8.0.0.dist-info/RECORD
kloudbuster-8.0.0.dist-info/WHEEL
kloudbuster-8.0.0.dist-info/entry_points.txt
kloudbuster-8.0.0.dist-info/metadata.json
kloudbuster-8.0.0.dist-info/pbr.json
kloudbuster-8.0.0.dist-info/top_level.txt
