Metadata-Version: 2.0
Name: kloudbuster
Version: 8.0.0
Summary: KloudBuster is an open source tool that allows anybody to load any Neutron OpenStack cloud at massive data plane scale swiftly and effortlessly.
Home-page: https://opendev.org/x/kloudbuster
Author: KloudBuster team at OpenStack
Author-email: kloudbuster-core@lists.launchpad.net
License: UNKNOWN
Platform: UNKNOWN
Classifier: Environment :: OpenStack
Classifier: Intended Audience :: Developers
Classifier: Intended Audience :: Information Technology
Classifier: Intended Audience :: System Administrators
Classifier: License :: OSI Approved :: Apache Software License
Classifier: Operating System :: POSIX :: Linux
Classifier: Operating System :: MacOS
Classifier: Programming Language :: Python
Classifier: Programming Language :: Python :: 3
Classifier: Programming Language :: Python :: 3.6
Requires-Python: >=3.6
Requires-Dist: Babel (>=2.3.4)
Requires-Dist: attrdict (>=2.0.0)
Requires-Dist: hdrhistogram (>=0.8.0)
Requires-Dist: ipaddress (>=1.0.16)
Requires-Dist: oslo.config (>=4.1.1)
Requires-Dist: oslo.log (>=3.26.1)
Requires-Dist: pbr (>=3.0.1)
Requires-Dist: pecan (>=1.2.1)
Requires-Dist: python-cinderclient (>=2.0.1)
Requires-Dist: python-glanceclient (>=2.6.0)
Requires-Dist: python-keystoneclient (>=3.10.0)
Requires-Dist: python-neutronclient (>=6.2.0)
Requires-Dist: python-novaclient (>=9.0.0)
Requires-Dist: python-openstackclient (>=3.11.0)
Requires-Dist: pytz (>=2016.4)
Requires-Dist: pyyaml (>=3.12)
Requires-Dist: redis (>=2.10.5)
Requires-Dist: tabulate (>=0.7.7)
